{
    "input_path": "/home/geonws/workspace/2026_project/roadsign_finder/paddleocr/test_file/Job_20250731_1053_Track13_Sphere_00683.jpg",
    "page_index": null,
    "model_settings": {
        "use_doc_preprocessor": true,
        "use_textline_orientation": true
    },
    "doc_preprocessor_res": {
        "input_path": null,
        "page_index": null,
        "model_settings": {
            "use_doc_orientation_classify": true,
            "use_doc_unwarping": true
        },
        "angle": 0
    },
    "dt_polys": [
        [
            [
                351,
                347
            ],
            [
                402,
                347
            ],
            [
                402,
                457
            ],
            [
                351,
                457
            ]
        ],
        [
            [
                344,
                467
            ],
            [
                403,
                473
            ],
            [
                399,
                519
            ],
            [
                339,
                513
            ]
        ],
        [
            [
                712,
                561
            ],
            [
                751,
                566
            ],
            [
                748,
                595
            ],
            [
                708,
                590
            ]
        ],
        [
            [
                750,
                581
            ],
            [
                773,
                581
            ],
            [
                773,
                598
            ],
            [
                750,
                598
            ]
        ],
        [
            [
                713,
                592
            ],
            [
                747,
                597
            ],
            [
                745,
                616
            ],
            [
                710,
                611
            ]
        ],
        [
            [
                617,
                966
            ],
            [
                672,
                966
            ],
            [
                672,
                984
            ],
            [
                617,
                984
            ]
        ],
        [
            [
                389,
                1503
            ],
            [
                481,
                1469
            ],
            [
                492,
                1501
            ],
            [
                400,
                1535
            ]
        ]
    ],
    "text_det_params": {
        "limit_side_len": 64,
        "limit_type": "min",
        "thresh": 0.3,
        "max_side_limit": 4000,
        "box_thresh": 0.6,
        "unclip_ratio": 1.5
    },
    "text_type": "general",
    "textline_orientation_angles": [
        0,
        0,
        0,
        0,
        0,
        0,
        0
    ],
    "text_rec_score_thresh": 0.0,
    "return_word_box": false,
    "rec_texts": [
        "7",
        "/진호시",
        "유교로",
        "101",
        "YugIU",
        "1911144",
        ""
    ],
    "rec_scores": [
        0.15501442551612854,
        0.6908426284790039,
        0.9706997871398926,
        0.6126058101654053,
        0.40231093764305115,
        0.49258217215538025,
        0.0
    ],
    "rec_polys": [
        [
            [
                351,
                347
            ],
            [
                402,
                347
            ],
            [
                402,
                457
            ],
            [
                351,
                457
            ]
        ],
        [
            [
                344,
                467
            ],
            [
                403,
                473
            ],
            [
                399,
                519
            ],
            [
                339,
                513
            ]
        ],
        [
            [
                712,
                561
            ],
            [
                751,
                566
            ],
            [
                748,
                595
            ],
            [
                708,
                590
            ]
        ],
        [
            [
                750,
                581
            ],
            [
                773,
                581
            ],
            [
                773,
                598
            ],
            [
                750,
                598
            ]
        ],
        [
            [
                713,
                592
            ],
            [
                747,
                597
            ],
            [
                745,
                616
            ],
            [
                710,
                611
            ]
        ],
        [
            [
                617,
                966
            ],
            [
                672,
                966
            ],
            [
                672,
                984
            ],
            [
                617,
                984
            ]
        ],
        [
            [
                389,
                1503
            ],
            [
                481,
                1469
            ],
            [
                492,
                1501
            ],
            [
                400,
                1535
            ]
        ]
    ],
    "rec_boxes": [
        [
            351,
            347,
            402,
            457
        ],
        [
            339,
            467,
            403,
            519
        ],
        [
            708,
            561,
            751,
            595
        ],
        [
            750,
            581,
            773,
            598
        ],
        [
            710,
            592,
            747,
            616
        ],
        [
            617,
            966,
            672,
            984
        ],
        [
            389,
            1469,
            492,
            1535
        ]
    ]
}